sam/__init__.py
sam/cli.py
sam/main.py
sam_cli-0.1.dist-info/METADATA
sam_cli-0.1.dist-info/WHEEL
sam_cli-0.1.dist-info/entry_points.txt
sam_cli-0.1.dist-info/top_level.txt
sam_cli-0.1.dist-info/RECORD
