Metadata-Version: 2.1
Name: sam-cli
Version: 0.1
Requires-Dist: antlr4-python3-runtime==4.7.2
Requires-Dist: luaparser==3.2.1
